LICENSE
MANIFEST.in
README.md
setup.cfg
setup.py
soundcheck_vlc/__init__.py
soundcheck_vlc/cli.py
soundcheck_vlc/main.py
soundcheck_vlc/register.py
soundcheck_vlc.egg-info/PKG-INFO
soundcheck_vlc.egg-info/SOURCES.txt
soundcheck_vlc.egg-info/dependency_links.txt
soundcheck_vlc.egg-info/entry_points.txt
soundcheck_vlc.egg-info/requires.txt
soundcheck_vlc.egg-info/top_level.txt
soundcheck_vlc/utils/__init__.py
soundcheck_vlc/utils/config.py
soundcheck_vlc/utils/parseinput.py
soundcheck_vlc/utils/video_parse.py
soundcheck_vlc/utils/vlchttp.py