Metadata-Version: 2.1
Name: soundcheck-vlc
Version: 0.1.5
Summary: Turns maston toots into a vlc playlist
Home-page: https://framagit.org/alfajet/soundcheck-vlc
Author: alfajet
Author-email: alfajet@protonmail.com
License:                     GNU GENERAL PUBLIC LICENSE
